saferoomcore/SafeExceptions.py
saferoomcore/Safenote.py
saferoomcore/ServiceManager.py
saferoomcore/__init__.py
saferoomcore/functions.py
saferoomcore/messages.py
saferoomcore/safevars.py
saferoomcore/tests.py
saferoomcore-0.6.dist-info/LICENSE
saferoomcore-0.6.dist-info/METADATA
saferoomcore-0.6.dist-info/WHEEL
saferoomcore-0.6.dist-info/dependency_links.txt
saferoomcore-0.6.dist-info/top_level.txt
saferoomcore-0.6.dist-info/RECORD
