Metadata-Version: 2.1
Name: saferoomcore
Version: 0.6
Summary: List of packages used in Saferoom Enterprise
Home-page: https://github.com/saferoombiz/saferoomcore
Author: Alexey Zelenkin
Author-email: alexey.zelenkin@gmail.com
License: MIT
Keywords: saferoom encryption decryption cms evernote onenote
Platform: UNKNOWN
Classifier: Development Status :: 3 - Alpha
Classifier: License :: OSI Approved :: MIT License
Classifier: Programming Language :: Python :: 3.6
Requires-Dist: requests
Requires-Dist: beautifulsoup4
Requires-Dist: evernote3
